{
  "main": {
    "id": "1dd6b6053c568a56",
    "type": "split",
    "children": [
      {
        "id": "edb0b573e0fbc304",
        "type": "tabs",
        "children": [
          {
            "id": "243f3c64f27c6064",
            "type": "leaf",
            "state": {
              "type": "image",
              "state": {
                "file": "public/assets/images/posts/post1.jpg"
              },
              "icon": "lucide-image",
              "title": "post1"
            }
          }
        ]
      }
    ],
    "direction": "vertical"
  },
  "left": {
    "id": "814a56c2d5e79cd7",
    "type": "split",
    "children": [
      {
        "id": "861705907342f6e4",
        "type": "tabs",
        "children": [
          {
            "id": "45733c6d102f2c34",
            "type": "leaf",
            "state": {
              "type": "file-explorer",
              "state": {
                "sortOrder": "alphabetical"
              },
              "icon": "lucide-folder-closed",
              "title": "Files"
            }
          },
          {
            "id": "fb265f81f91b22cd",
            "type": "leaf",
            "state": {
              "type": "search",
              "state": {
                "query": "",
                "matchingCase": false,
                "explainSearch": false,
                "collapseAll": false,
                "extraContext": false,
                "sortOrder": "alphabetical"
              },
              "icon": "lucide-search",
              "title": "Search"
            }
          },
          {
            "id": "acdea44a64005650",
            "type": "leaf",
            "state": {
              "type": "bookmarks",
              "state": {},
              "icon": "lucide-bookmark",
              "title": "Bookmarks"
            }
          }
        ]
      }
    ],
    "direction": "horizontal",
    "width": 300
  },
  "right": {
    "id": "8e4ecd584109a2e6",
    "type": "split",
    "children": [
      {
        "id": "f3b6897ff92fc718",
        "type": "tabs",
        "children": [
          {
            "id": "7f238be4526d5de4",
            "type": "leaf",
            "state": {
              "type": "backlink",
              "state": {
                "file": "README.md",
                "collapseAll": false,
                "extraContext": false,
                "sortOrder": "alphabetical",
                "showSearch": false,
                "searchQuery": "",
                "backlinkCollapsed": false,
                "unlinkedCollapsed": true
              },
              "icon": "links-coming-in",
              "title": "Backlinks for README"
            }
          },
          {
            "id": "b90560b0133f8296",
            "type": "leaf",
            "state": {
              "type": "outgoing-link",
              "state": {
                "file": "README.md",
                "linksCollapsed": false,
                "unlinkedCollapsed": true
              },
              "icon": "links-going-out",
              "title": "Outgoing links from README"
            }
          },
          {
            "id": "58b2c1bdaede4391",
            "type": "leaf",
            "state": {
              "type": "tag",
              "state": {
                "sortOrder": "frequency",
                "useHierarchy": true
              },
              "icon": "lucide-tags",
              "title": "Tags"
            }
          },
          {
            "id": "59c73023f5daa626",
            "type": "leaf",
            "state": {
              "type": "outline",
              "state": {
                "file": "README.md"
              },
              "icon": "lucide-list",
              "title": "Outline of README"
            }
          }
        ]
      }
    ],
    "direction": "horizontal",
    "width": 300,
    "collapsed": true
  },
  "left-ribbon": {
    "hiddenItems": {
      "switcher:Open quick switcher": false,
      "graph:Open graph view": false,
      "canvas:Create new canvas": false,
      "daily-notes:Open today's daily note": false,
      "templates:Insert template": false,
      "command-palette:Open command palette": false
    }
  },
  "active": "243f3c64f27c6064",
  "lastOpenFiles": [
    "public/assets/images/about/coder.jpg",
    "public/assets/images/mice/hashed.png",
    "public/assets/images/mice/exp.png",
    "README.md",
    "public/assets/images/mice/Screenshot 2025-12-21 at 07.46.31.png",
    "src/content/posts/typescript-best-practices.md",
    "src/content/posts/testing-strategies.md",
    "src/content/posts/state-management.md",
    "src/content/posts/react-performance.md",
    "src/content/posts/nodejs-microservices.md",
    "src/content/posts/nextjs-14-guide.md",
    "src/content/posts/graphql-api-design.md",
    "src/content/posts/git-workflow.md",
    "src/content/posts/docker-basics.md",
    "src/content/posts/devops-cicd.md",
    "src/content/posts/database-design.md",
    "src/content/posts/css-modern-techniques.md",
    "src/content/posts/api-security.md",
    "src/content/posts/accessibility-guide.md",
    "src/content/posts/Spider Society PGP.md",
    "src/content/posts/Shenzi PGP.md",
    "src/content/posts/Mice PGP.md"
  ]
}